unitrack/__init__.py
unitrack/_memory.py
unitrack/_stateful.py
unitrack/_tracker.py
unitrack/consts.py
unitrack/costs.py
unitrack/debug.py
unitrack/py.typed
unitrack/assignment/__init__.py
unitrack/assignment/_auction.py
unitrack/assignment/_base.py
unitrack/assignment/_greedy.py
unitrack/assignment/_hungarian.py
unitrack/assignment/_jonker.py
unitrack/assignment/_utils.py
unitrack/stages/__init__.py
unitrack/stages/association.py
unitrack/stages/base_stage.py
unitrack/stages/gate.py
unitrack/stages/lost.py
unitrack/states/__init__.py
unitrack/states/base_state.py
unitrack/states/value.py
unitrack-4.7.2.dist-info/LICENSE
unitrack-4.7.2.dist-info/METADATA
unitrack-4.7.2.dist-info/WHEEL
unitrack-4.7.2.dist-info/top_level.txt
unitrack-4.7.2.dist-info/RECORD
