Metadata-Version: 2.1
Name: unitrack
Version: 4.7.2
Summary: A multi-stage object tracking framework
Author-email: Kurt Stolle <k.h.w.stolle@gmail.com>
Keywords: perception,computer vision,deep learning,object detection,instance segmentation,semantic segmentation
Classifier: Development Status :: 4 - Beta
Classifier: Programming Language :: Python
Classifier: Programming Language :: Python :: 3.11
Classifier: Programming Language :: Python :: 3.12
Classifier: Programming Language :: Python :: Implementation :: CPython
Requires-Python: >=3.10
License-File: LICENSE
Requires-Dist: torch >=2.2.2
Requires-Dist: scikit-learn >=1.2.2
Requires-Dist: tensordict >=0.3.2
Requires-Dist: unipercept
Provides-Extra: docs
Requires-Dist: sphinx ; extra == 'docs'
Requires-Dist: sphinx-rtd-theme ; extra == 'docs'
Requires-Dist: numpydoc ; extra == 'docs'
Provides-Extra: notebooks
Requires-Dist: jupyterlab ; extra == 'notebooks'
Requires-Dist: ipywidgets ; extra == 'notebooks'
Requires-Dist: ipykernel ; extra == 'notebooks'
Requires-Dist: ipython-autotime ; extra == 'notebooks'
Requires-Dist: matplotlib >=3.8.4 ; extra == 'notebooks'
Requires-Dist: seaborn >=0.13.2 ; extra == 'notebooks'
Provides-Extra: qa
Requires-Dist: black >=24.3.0 ; extra == 'qa'
Requires-Dist: bandit[toml] ; extra == 'qa'
Requires-Dist: check-manifest ; extra == 'qa'
Requires-Dist: flake8 >=7.0.0 ; extra == 'qa'
Requires-Dist: flake8-bugbear ; extra == 'qa'
Requires-Dist: flake8-docstrings ; extra == 'qa'
Requires-Dist: flake8-formatter-junit-xml ; extra == 'qa'
Requires-Dist: flake8-import-conventions ; extra == 'qa'
Requires-Dist: flake8-unused-arguments ; extra == 'qa'
Requires-Dist: flake8-comprehensions ; extra == 'qa'
Requires-Dist: flake8-errmsg ; extra == 'qa'
Requires-Dist: flake8-logging-format ; extra == 'qa'
Requires-Dist: flake8-pie ; extra == 'qa'
Requires-Dist: flake8-pyi ; extra == 'qa'
Requires-Dist: flake8-pytest-style ; extra == 'qa'
Requires-Dist: flake8-return ; extra == 'qa'
Requires-Dist: flake8-2020 ; extra == 'qa'
Requires-Dist: flake8-executable ; extra == 'qa'
Requires-Dist: flake8-simplify ; extra == 'qa'
Requires-Dist: flake8-black ; extra == 'qa'
Requires-Dist: flake8-pyproject ; extra == 'qa'
Requires-Dist: pre-commit ; extra == 'qa'
Requires-Dist: pygrep ; extra == 'qa'
Requires-Dist: isort >=5.13.2 ; extra == 'qa'
Requires-Dist: refurb ; extra == 'qa'
Requires-Dist: pylint >=3.0.3 ; extra == 'qa'
Requires-Dist: pylint-junit ; extra == 'qa'
Requires-Dist: shellcheck-py ; extra == 'qa'
Requires-Dist: pylint ; extra == 'qa'
Requires-Dist: mypy >=1.9.0 ; extra == 'qa'
Requires-Dist: autoflake ; extra == 'qa'
Requires-Dist: pydocstyle ; extra == 'qa'
Requires-Dist: pyre-check ; extra == 'qa'
Requires-Dist: pydocstringformatter ; extra == 'qa'
Requires-Dist: pyrefact ; extra == 'qa'
Requires-Dist: pyflakes ; extra == 'qa'
Requires-Dist: mccabe ; extra == 'qa'
Provides-Extra: tests
Requires-Dist: hypothesis >=6.100.1 ; extra == 'tests'
Requires-Dist: pytest >=8.1.1 ; extra == 'tests'
Requires-Dist: pytest-sugar ; extra == 'tests'
Requires-Dist: pytest-xdist ; extra == 'tests'
Requires-Dist: pytest-benchmark ; extra == 'tests'
Requires-Dist: pytest-cov ; extra == 'tests'
Requires-Dist: pytest-mock ; extra == 'tests'
Requires-Dist: pytest-runner ; extra == 'tests'
Requires-Dist: pytest-github-actions-annotate-failures ; extra == 'tests'
